keras_model_specs/__init__.py
keras_model_specs/model_spec.py
keras_model_specs/model_specs.json
keras_model_specs-2.1.1.dist-info/LICENSE
keras_model_specs-2.1.1.dist-info/METADATA
keras_model_specs-2.1.1.dist-info/WHEEL
keras_model_specs-2.1.1.dist-info/top_level.txt
keras_model_specs-2.1.1.dist-info/RECORD
