Metadata-Version: 2.1
Name: keras-model-specs
Version: 2.1.1
Summary: A helper package for managing keras model base architectures (from keras_applications) with overrides for target size and preprocessing functions.
Home-page: https://www.triage.com/
Author: Triage Technologies Inc.
Author-email: ai@triage.com
License: UNKNOWN
Platform: UNKNOWN
Requires-Dist: keras
Requires-Dist: h5py
Requires-Dist: Pillow
Requires-Dist: six
